{
  "internalAPI": {
    "entity_kent_c_dodds": {
      "id": "kent_c_dodds",
      "homepage": {
        "name": "https://kentcdodds.com/blog/",
        "url": "https://kentcdodds.com/blog/"
      },
      "name": "Kent C. Dodds",
      "nameClean": null,
      "twitterName": "kentcdodds",
      "twitter": {
        "userName": "kentcdodds",
        "avatarUrl": "https://pbs.twimg.com/profile_images/1567269493608714241/6ACZo99k.jpg",
        "id": "389681470",
        "description": "Improving the world with quality software 路 Husband, Father, Latter-day Saint, Teacher, OSS 路 https://t.co/pPQmnZS6rR 路 https://t.co/7KDAxIs02L 路 https://t.co/U5KafpJTZp"
      }
    }
  }
}